redditcommentcloud/__init__.py
redditcommentcloud/cocl.py
redditcommentcloud/config.py
redditcommentcloud-0.1.1.dist-info/LICENSE
redditcommentcloud-0.1.1.dist-info/METADATA
redditcommentcloud-0.1.1.dist-info/WHEEL
redditcommentcloud-0.1.1.dist-info/top_level.txt
redditcommentcloud-0.1.1.dist-info/RECORD
