Metadata-Version: 2.1
Name: redditcommentcloud
Version: 0.1.1
Summary: Python3.7+ wrapper for generating word clouds from a Reddit user's comments.
Home-page: https://github.com/chmey/reddit-comment-cloud
Author: Christoph Meyer
Author-email: christoph@chmey.com
License: GPLv3
Keywords: reddit,wordcloud
Platform: UNKNOWN
Classifier: Development Status :: 4 - Beta
Classifier: Intended Audience :: Developers
Classifier: License :: OSI Approved :: GNU General Public License v3 or later (GPLv3+)
Classifier: Programming Language :: Python :: 3
Requires-Python: >=3
Requires-Dist: matplotlib
Requires-Dist: praw
Requires-Dist: WordCloud
